miniabm/__init__.py
miniabm/miniabm.py
miniabm-0.0.1.dist-info/METADATA
miniabm-0.0.1.dist-info/WHEEL
miniabm-0.0.1.dist-info/top_level.txt
miniabm-0.0.1.dist-info/RECORD
